{
  "title": "House; Struss Residence, Ross Township, PA; [floor plan, notes]",
  "creation_date": "1990-1991",
  "creation_date_earliest": "1990-01-01",
  "creation_date_latest": "1991-01-01",
  "medium": "pencil and ink on tracing paper",
  "accession_number": "94.197.3",
  "id": "cmoa:things/6eed3a47-f440-4740-a98c-1c8a542e0e57",
  "credit_line": "Gift of Robert Dale Lynch",
  "date_acquired": "1994-09-22",
  "department": "Heinz Architectural Center",
  "physical_location": "Not on View",
  "item_width": 36.0,
  "item_height": 24.0,
  "item_depth": 0.0,
  "item_diameter": 0.0,
  "web_url": "http://collection.cmoa.org/CollectionDetail.aspx?item=1034607",
  "provenance_text": "Robert Dale Lynch, Pittsburgh, PA",
  "classification": "drawings and watercolors",
  "images": null,
  "creator": null
}
